{"v":"5.5.7","meta":{"g":"LottieFiles AE 0.1.20","a":"","k":"","d":"","tc":""},"fr":29.9700012207031,"ip":0,"op":120.0000048877,"w":1200,"h":1200,"nm":"Comp 1","ddd":0,"assets":[],"layers":[{"ddd":0,"ind":1,"ty":4,"nm":"R Mask","parent":3,"td":1,"sr":1,"ks":{"o":{"a":0,"k":100,"ix":11},"r":{"a":0,"k":0,"ix":10},"p":{"a":0,"k":[0,0,0],"ix":2},"a":{"a":0,"k":[0,0,0],"ix":1},"s":{"a":0,"k":[100,100,100],"ix":6}},"ao":0,"shapes":[{"ty":"gr","it":[{"ind":0,"ty":"sh","ix":1,"ks":{"a":0,"k":{"i":[[-273.847,-181.712],[50.5,-27.89],[27.89,50.5],[-50.5,27.89],[-76.56800000000001,53.06]],"o":[[143.453,-326.276],[50.5,27.89],[-27.89,50.5],[-50.5,-6.794],[-168.55599999999998,-16.231]],"v":[[-33.274,-265.053],[50.5,0],[0,50.5],[-50.5,0],[-98.977,36.18]],"c":true},"ix":2},"nm":"Path 1","mn":"ADBE Vector Shape - Group","hd":false,"_render":true},{"ty":"fl","c":{"a":0,"k":[0.264,0.3984,0.936,1],"ix":4},"o":{"a":0,"k":100,"ix":5},"r":1,"bm":0,"nm":"Fill 1","mn":"ADBE Vector Graphic - Fill","hd":false,"_render":true},{"ty":"tr","p":{"a":0,"k":[0.274,-45.756],"ix":2},"a":{"a":0,"k":[0,0],"ix":1},"s":{"a":0,"k":[100,100],"ix":3},"r":{"a":0,"k":0,"ix":6},"o":{"a":0,"k":100,"ix":7},"sk":{"a":0,"k":0,"ix":4},"sa":{"a":0,"k":0,"ix":5},"nm":"Transform","_render":true}],"nm":"Ch hole 2","np":3,"cix":2,"bm":0,"ix":1,"mn":"ADBE Vector Group","hd":false,"_render":true}],"ip":0,"op":120.0000048877,"st":0,"bm":0,"completed":true},{"ddd":0,"ind":2,"ty":4,"nm":"R Character","parent":1,"tt":1,"sr":1,"ks":{"o":{"a":1,"k":[{"i":{"x":[0.95],"y":[1]},"o":{"x":[1],"y":[0]},"t":99.889,"s":[100]},{"t":120.0000048877,"s":[0]}],"ix":11},"r":{"a":0,"k":-3,"ix":10},"p":{"a":0,"k":[-1.452,-73.024,0],"ix":2},"a":{"a":0,"k":[293.372,57,0],"ix":1},"s":{"a":0,"k":[100,100,100],"ix":6}},"ao":0,"shapes":[{"ty":"gr","it":[{"ty":"gr","it":[{"ind":0,"ty":"sh","ix":1,"ks":{"a":1,"k":[{"i":{"x":0,"y":1},"o":{"x":0.05,"y":0},"t":20.111,"s":[{"i":[[314,43.5],[316.23,89.81],[263.441,79.825]],"o":[[314,43.5],[316.23,89.81],[263.441,79.825]],"v":[[314,43.5],[316.23,89.81],[263.441,79.825]],"c":false}]},{"t":29.4975012014578,"s":[{"i":[[314,43.5],[324.5,86],[299,135]],"o":[[314,43.5],[324.5,86],[299,135]],"v":[[314,43.5],[324.5,86],[299,135]],"c":false}]}],"ix":2},"nm":"Path 2","mn":"ADBE Vector Shape - Group","hd":false,"_render":true},{"ty":"st","c":{"a":0,"k":[0.3118,0.4391,0.9482,1],"ix":3},"o":{"a":0,"k":100,"ix":4},"w":{"a":0,"k":40,"ix":5},"lc":1,"lj":2,"bm":0,"d":[{"n":"d","nm":"dash","v":{"a":0,"k":149,"ix":1}},{"n":"g","nm":"gap","v":{"a":0,"k":118,"ix":2}},{"n":"o","nm":"offset","v":{"a":0,"k":-236,"ix":7}}],"nm":"Shirt","mn":"ADBE Vector Graphic - Stroke","hd":false,"_render":true},{"ty":"st","c":{"a":0,"k":[0.3118,0.4391,0.9482,1],"ix":3},"o":{"a":0,"k":100,"ix":4},"w":{"a":0,"k":40,"ix":5},"lc":2,"lj":2,"bm":0,"d":[{"n":"d","nm":"dash","v":{"a":0,"k":149,"ix":1}},{"n":"g","nm":"gap","v":{"a":0,"k":118,"ix":2}},{"n":"o","nm":"offset","v":{"a":0,"k":-173,"ix":7}}],"nm":"Shirt 2","mn":"ADBE Vector Graphic - Stroke","hd":false,"_render":true},{"ty":"st","c":{"a":0,"k":[0.2456,0.3834,0.9344,1],"ix":3},"o":{"a":0,"k":100,"ix":4},"w":{"a":0,"k":33,"ix":5},"lc":2,"lj":2,"bm":0,"d":[{"n":"d","nm":"dash","v":{"a":0,"k":111,"ix":1}},{"n":"g","nm":"gap","v":{"a":0,"k":118,"ix":2}},{"n":"o","nm":"offset","v":{"a":0,"k":-43,"ix":7}}],"nm":"Skin","mn":"ADBE Vector Graphic - Stroke","hd":false,"_render":true},{"ty":"tr","p":{"a":0,"k":[0,0],"ix":2},"a":{"a":0,"k":[0,0],"ix":1},"s":{"a":0,"k":[100,100],"ix":3},"r":{"a":0,"k":0,"ix":6},"o":{"a":0,"k":100,"ix":7},"sk":{"a":0,"k":0,"ix":4},"sa":{"a":0,"k":0,"ix":5},"nm":"Transform","_render":true}],"nm":"L Hand","np":5,"cix":2,"bm":0,"ix":1,"mn":"ADBE Vector Group","hd":false,"_render":true},{"ty":"gr","it":[{"ty":"gr","it":[{"ind":0,"ty":"sh","ix":1,"ks":{"a":0,"k":{"i":[[-22.091,-35],[36,-15.329999999999998],[26.091,24],[-40,19.33]],"o":[[22.091,-35],[36,23.33],[-18.091,24],[-40,-19.33]],"v":[[0,-35],[36,4],[4,24],[-40,0]],"c":true},"ix":2},"nm":"Path 1","mn":"ADBE Vector Shape - Group","hd":false,"_render":true},{"ty":"fl","c":{"a":0,"k":[0.161,0.4571,0.539,1],"ix":4},"o":{"a":0,"k":100,"ix":5},"r":1,"bm":0,"nm":"Fill 1","mn":"ADBE Vector Graphic - Fill","hd":false,"_render":true},{"ty":"tr","p":{"a":0,"k":[285,-46],"ix":2},"a":{"a":0,"k":[0,0],"ix":1},"s":{"a":0,"k":[100,100],"ix":3},"r":{"a":0,"k":0,"ix":6},"o":{"a":0,"k":100,"ix":7},"sk":{"a":0,"k":0,"ix":4},"sa":{"a":0,"k":0,"ix":5},"nm":"Transform","_render":true}],"nm":"Ellipse 1","np":3,"cix":2,"bm":0,"ix":1,"mn":"ADBE Vector Group","hd":false,"_render":true},{"ty":"gr","it":[{"ind":0,"ty":"sh","ix":1,"ks":{"a":0,"k":{"i":[[246.5,-52.5],[210.541,-43.525999999999996],[270,-23]],"o":[[246.5,-52.5],[233.5,-7],[276,-23]],"v":[[246.5,-52.5],[222.5,-24.5],[273,-23]],"c":true},"ix":2},"nm":"Path 1","mn":"ADBE Vector Shape - Group","hd":false,"_render":true},{"ty":"fl","c":{"a":0,"k":[0.161,0.4571,0.539,1],"ix":4},"o":{"a":0,"k":100,"ix":5},"r":1,"bm":0,"nm":"Fill 1","mn":"ADBE Vector Graphic - Fill","hd":false,"_render":true},{"ty":"tr","p":{"a":0,"k":[0,0],"ix":2},"a":{"a":0,"k":[0,0],"ix":1},"s":{"a":0,"k":[100,100],"ix":3},"r":{"a":0,"k":0,"ix":6},"o":{"a":0,"k":100,"ix":7},"sk":{"a":0,"k":0,"ix":4},"sa":{"a":0,"k":0,"ix":5},"nm":"Transform","_render":true}],"nm":"Shape 3","np":3,"cix":2,"bm":0,"ix":2,"mn":"ADBE Vector Group","hd":false,"_render":true},{"ty":"tr","p":{"a":0,"k":[265.532,-63.657],"ix":2},"a":{"a":0,"k":[270.532,-48.657],"ix":1},"s":{"a":0,"k":[113.445,89.877],"ix":3},"r":{"a":0,"k":0,"ix":6},"o":{"a":0,"k":100,"ix":7},"sk":{"a":0,"k":0,"ix":4},"sa":{"a":0,"k":0,"ix":5},"nm":"Transform","_render":true}],"nm":"Cap","np":2,"cix":2,"bm":0,"ix":2,"mn":"ADBE Vector Group","hd":false,"_render":true},{"ty":"gr","it":[{"ind":0,"ty":"sh","ix":1,"ks":{"a":0,"k":{"i":[[286,14],[280,-38]],"o":[[286,14],[280,-38]],"v":[[286,14],[280,-38]],"c":false},"ix":2},"nm":"Path 1","mn":"ADBE Vector Shape - Group","hd":false,"_render":true},{"ty":"st","c":{"a":0,"k":[0.2456,0.3834,0.9344,1],"ix":3},"o":{"a":0,"k":100,"ix":4},"w":{"a":0,"k":73,"ix":5},"lc":2,"lj":1,"ml":4,"bm":0,"d":[{"n":"d","nm":"dash","v":{"a":0,"k":39,"ix":1}},{"n":"g","nm":"gap","v":{"a":0,"k":99,"ix":2}},{"n":"o","nm":"offset","v":{"a":0,"k":-45,"ix":7}}],"nm":"Stroke 1","mn":"ADBE Vector Graphic - Stroke","hd":false,"_render":true},{"ty":"st","c":{"a":0,"k":[0.2456,0.3834,0.9344,1],"ix":3},"o":{"a":0,"k":100,"ix":4},"w":{"a":0,"k":33,"ix":5},"lc":2,"lj":1,"ml":4,"bm":0,"nm":"Stroke 2","mn":"ADBE Vector Graphic - Stroke","hd":false,"_render":true},{"ty":"tr","p":{"a":0,"k":[0,0],"ix":2},"a":{"a":0,"k":[0,0],"ix":1},"s":{"a":0,"k":[100,100],"ix":3},"r":{"a":0,"k":0,"ix":6},"o":{"a":0,"k":100,"ix":7},"sk":{"a":0,"k":0,"ix":4},"sa":{"a":0,"k":0,"ix":5},"nm":"Transform","_render":true}],"nm":"Face","np":4,"cix":2,"bm":0,"ix":3,"mn":"ADBE Vector Group","hd":false,"_render":true},{"ty":"gr","it":[{"ind":0,"ty":"sh","ix":1,"ks":{"a":0,"k":{"i":[[347.62,-4.872],[244,94],[266,152],[343,136]],"o":[[226,14],[254,134],[320,152],[345,94]],"v":[[284,5],[249,114],[293,152],[344,115]],"c":true},"ix":2},"nm":"Path 1","mn":"ADBE Vector Shape - Group","hd":false,"_render":true},{"ty":"fl","c":{"a":0,"k":[0.34,0.472,1,1],"ix":4},"o":{"a":0,"k":100,"ix":5},"r":1,"bm":0,"nm":"Fill 1","mn":"ADBE Vector Graphic - Fill","hd":false,"_render":true},{"ty":"tr","p":{"a":0,"k":[0,0],"ix":2},"a":{"a":0,"k":[0,0],"ix":1},"s":{"a":0,"k":[100,100],"ix":3},"r":{"a":0,"k":0,"ix":6},"o":{"a":0,"k":100,"ix":7},"sk":{"a":0,"k":0,"ix":4},"sa":{"a":0,"k":0,"ix":5},"nm":"Transform","_render":true}],"nm":"Body","np":3,"cix":2,"bm":0,"ix":4,"mn":"ADBE Vector Group","hd":false,"_render":true},{"ty":"gr","it":[{"ind":0,"ty":"sh","ix":1,"ks":{"a":1,"k":[{"i":{"x":0,"y":1},"o":{"x":0.05,"y":0},"t":20.113,"s":[{"i":[[263,38],[204.255,14.31],[179.834,-56.659]],"o":[[263,38],[204.255,14.31],[179.834,-56.659]],"v":[[263,38],[204.255,14.31],[179.834,-56.659]],"c":false}]},{"t":29.4975012014578,"s":[{"i":[[263,38],[213.255,85.31],[198.834,23.341]],"o":[[263,38],[213.255,85.31],[198.834,23.341]],"v":[[263,38],[213.255,85.31],[198.834,23.341]],"c":false}]}],"ix":2},"nm":"Path 1","mn":"ADBE Vector Shape - Group","hd":false,"_render":true},{"ty":"st","c":{"a":0,"k":[0.3118,0.4391,0.9482,1],"ix":3},"o":{"a":0,"k":100,"ix":4},"w":{"a":0,"k":40,"ix":5},"lc":1,"lj":2,"bm":0,"d":[{"n":"d","nm":"dash","v":{"a":0,"k":149,"ix":1}},{"n":"g","nm":"gap","v":{"a":0,"k":118,"ix":2}},{"n":"o","nm":"offset","v":{"a":0,"k":-236,"ix":7}}],"nm":"Shirt","mn":"ADBE Vector Graphic - Stroke","hd":false,"_render":true},{"ty":"st","c":{"a":0,"k":[0.3118,0.4391,0.9482,1],"ix":3},"o":{"a":0,"k":100,"ix":4},"w":{"a":0,"k":40,"ix":5},"lc":2,"lj":2,"bm":0,"d":[{"n":"d","nm":"dash","v":{"a":0,"k":149,"ix":1}},{"n":"g","nm":"gap","v":{"a":0,"k":118,"ix":2}},{"n":"o","nm":"offset","v":{"a":0,"k":-173,"ix":7}}],"nm":"Shirt 2","mn":"ADBE Vector Graphic - Stroke","hd":false,"_render":true},{"ty":"st","c":{"a":0,"k":[0.2456,0.3834,0.9344,1],"ix":3},"o":{"a":0,"k":100,"ix":4},"w":{"a":0,"k":33,"ix":5},"lc":2,"lj":2,"bm":0,"d":[{"n":"d","nm":"dash","v":{"a":0,"k":111,"ix":1}},{"n":"g","nm":"gap","v":{"a":0,"k":118,"ix":2}},{"n":"o","nm":"offset","v":{"a":0,"k":-43,"ix":7}}],"nm":"Skin","mn":"ADBE Vector Graphic - Stroke","hd":false,"_render":true},{"ty":"tr","p":{"a":0,"k":[0,0],"ix":2},"a":{"a":0,"k":[0,0],"ix":1},"s":{"a":0,"k":[100,100],"ix":3},"r":{"a":0,"k":0,"ix":6},"o":{"a":0,"k":100,"ix":7},"sk":{"a":0,"k":0,"ix":4},"sa":{"a":0,"k":0,"ix":5},"nm":"Transform","_render":true}],"nm":"R hand","np":5,"cix":2,"bm":0,"ix":5,"mn":"ADBE Vector Group","hd":false,"_render":true},{"ty":"gr","it":[{"ty":"gr","it":[{"ind":0,"ty":"sh","ix":1,"ks":{"a":0,"k":{"i":[[194,-13],[198.375,-14.875],[216.549,-12.167],[225.359,32.503],[221.5,34.5],[213,-10]],"o":[[194,-13],[198.375,-14.875],[216.549,-12.167],[225.359,32.503],[221.5,34.5],[213,-10]],"v":[[194,-13],[198.375,-14.875],[216.549,-12.167],[225.359,32.503],[221.5,34.5],[213,-10]],"c":true},"ix":2},"nm":"Path 1","mn":"ADBE Vector Shape - Group","hd":false,"_render":true},{"ty":"fl","c":{"a":0,"k":[0,0.7765,1,1],"ix":4},"o":{"a":0,"k":100,"ix":5},"r":1,"bm":0,"nm":"Fill 1","mn":"ADBE Vector Graphic - Fill","hd":false,"_render":true},{"ty":"tr","p":{"a":0,"k":[0,0],"ix":2},"a":{"a":0,"k":[0,0],"ix":1},"s":{"a":0,"k":[100,100],"ix":3},"r":{"a":0,"k":0,"ix":6},"o":{"a":0,"k":100,"ix":7},"sk":{"a":0,"k":0,"ix":4},"sa":{"a":0,"k":0,"ix":5},"nm":"Transform","_render":true}],"nm":"Shape 5","np":3,"cix":2,"bm":0,"ix":1,"mn":"ADBE Vector Group","hd":false,"_render":true},{"ty":"gr","it":[{"ind":0,"ty":"sh","ix":1,"ks":{"a":0,"k":{"i":[[194,-13],[204,31],[221.5,34.5],[213,-10]],"o":[[194,-13],[204,31],[221.5,34.5],[213,-10]],"v":[[194,-13],[204,31],[221.5,34.5],[213,-10]],"c":true},"ix":2},"nm":"Path 1","mn":"ADBE Vector Shape - Group","hd":false,"_render":true},{"ty":"fl","c":{"a":0,"k":[0.161,0.4571,0.539,1],"ix":4},"o":{"a":0,"k":100,"ix":5},"r":1,"bm":0,"nm":"Fill 1","mn":"ADBE Vector Graphic - Fill","hd":false,"_render":true},{"ty":"tr","p":{"a":0,"k":[0,0],"ix":2},"a":{"a":0,"k":[0,0],"ix":1},"s":{"a":0,"k":[100,100],"ix":3},"r":{"a":0,"k":0,"ix":6},"o":{"a":0,"k":100,"ix":7},"sk":{"a":0,"k":0,"ix":4},"sa":{"a":0,"k":0,"ix":5},"nm":"Transform","_render":true}],"nm":"Shape 4","np":3,"cix":2,"bm":0,"ix":2,"mn":"ADBE Vector Group","hd":false,"_render":true},{"ty":"tr","p":{"a":1,"k":[{"i":{"x":0,"y":1},"o":{"x":0.05,"y":0},"t":20.113,"s":[194.19,-69.316],"to":[2.582,13.188],"ti":[-2.582,-13.188]},{"t":29.4975012014578,"s":[209.68,9.813]}],"ix":2},"a":{"a":0,"k":[209.68,9.813],"ix":1},"s":{"a":0,"k":[100,100],"ix":3},"r":{"a":0,"k":0,"ix":6},"o":{"a":0,"k":100,"ix":7},"sk":{"a":0,"k":0,"ix":4},"sa":{"a":0,"k":0,"ix":5},"nm":"Transform","_render":true}],"nm":"Ph","np":3,"cix":2,"bm":0,"ix":6,"mn":"ADBE Vector Group","hd":false,"_render":true},{"ty":"tr","p":{"a":0,"k":[303.165,131.637],"ix":2},"a":{"a":0,"k":[303.165,131.637],"ix":1},"s":{"a":1,"k":[{"i":{"x":[0,0],"y":[1,1]},"o":{"x":[0.05,0.05],"y":[0,0]},"t":9.385,"s":[0,0]},{"t":29.4975012014578,"s":[100,100]}],"ix":3},"r":{"a":1,"k":[{"i":{"x":[0],"y":[1]},"o":{"x":[0.05],"y":[0]},"t":9.385,"s":[26]},{"t":29.4975012014578,"s":[0]}],"ix":6},"o":{"a":0,"k":100,"ix":7},"sk":{"a":0,"k":0,"ix":4},"sa":{"a":0,"k":0,"ix":5},"nm":"Transform","_render":true}],"nm":"Group 1","np":6,"cix":2,"bm":0,"ix":1,"mn":"ADBE Vector Group","hd":false,"_render":true}],"ip":0,"op":120.0000048877,"st":0,"bm":0,"completed":true},{"ddd":0,"ind":3,"ty":4,"nm":"R Chat Box","parent":9,"sr":1,"ks":{"o":{"a":1,"k":[{"i":{"x":[0.95],"y":[1]},"o":{"x":[1],"y":[0]},"t":99.889,"s":[100]},{"t":120.0000048877,"s":[0]}],"ix":11},"r":{"a":1,"k":[{"i":{"x":[0],"y":[1]},"o":{"x":[0.05],"y":[0]},"t":0,"s":[-59]},{"i":{"x":[0],"y":[1]},"o":{"x":[0.05],"y":[0]},"t":40.224,"s":[3]},{"t":99.8887540685522,"s":[3]}],"ix":10},"p":{"a":1,"k":[{"i":{"x":0,"y":1},"o":{"x":0.05,"y":0},"t":40.224,"s":[666.75,788.25,0],"to":[-10,-50.667,0],"ti":[10,50.667,0]},{"t":119.330004860411,"s":[606.75,484.25,0]}],"ix":2},"a":{"a":0,"k":[-131.627,87.008,0],"ix":1},"s":{"a":1,"k":[{"i":{"x":[0,0,0],"y":[1,1,1]},"o":{"x":[0.05,0.05,0.05],"y":[0,0,0]},"t":0,"s":[0,0,100]},{"i":{"x":[0,0,0],"y":[1,1,1]},"o":{"x":[0.05,0.05,0.05],"y":[0,0,0]},"t":40.224,"s":[100,100,100]},{"t":119.330004860411,"s":[100,100,100]}],"ix":6}},"ao":0,"shapes":[{"ty":"gr","it":[{"ind":0,"ty":"sh","ix":1,"ks":{"a":0,"k":{"i":[[-181.332,17.514],[-159.519,13.367]],"o":[[-181.332,17.514],[-159.519,13.367]],"v":[[-181.332,17.514],[-159.519,13.367]],"c":false},"ix":2},"nm":"Path 1","mn":"ADBE Vector Shape - Group","hd":false,"_render":true},{"ty":"st","c":{"a":0,"k":[0.161,0.4571,0.539,1],"ix":3},"o":{"a":0,"k":100,"ix":4},"w":{"a":0,"k":22,"ix":5},"lc":2,"lj":1,"ml":4,"bm":0,"d":[{"n":"d","nm":"dash","v":{"a":0,"k":204,"ix":1}},{"n":"g","nm":"gap","v":{"a":0,"k":307,"ix":2}},{"n":"o","nm":"offset","v":{"a":1,"k":[{"i":{"x":[0],"y":[1]},"o":{"x":[0.05],"y":[0]},"t":62.346,"s":[241]},{"t":86.4800035224026,"s":[98]}],"ix":7}}],"nm":"Stroke 1","mn":"ADBE Vector Graphic - Stroke","hd":false,"_render":true},{"ty":"tr","p":{"a":0,"k":[0,0],"ix":2},"a":{"a":0,"k":[0,0],"ix":1},"s":{"a":0,"k":[100,100],"ix":3},"r":{"a":0,"k":0,"ix":6},"o":{"a":0,"k":100,"ix":7},"sk":{"a":0,"k":0,"ix":4},"sa":{"a":0,"k":0,"ix":5},"nm":"Transform","_render":true}],"nm":"Shape 3","np":3,"cix":2,"bm":0,"ix":1,"mn":"ADBE Vector Group","hd":false,"_render":true},{"ty":"gr","it":[{"ind":0,"ty":"sh","ix":1,"ks":{"a":0,"k":{"i":[[-185.793,-10.29],[-137.279,-20.844]],"o":[[-185.793,-10.29],[-137.279,-20.844]],"v":[[-185.793,-10.29],[-137.279,-20.844]],"c":false},"ix":2},"nm":"Path 1","mn":"ADBE Vector Shape - Group","hd":false,"_render":true},{"ty":"st","c":{"a":0,"k":[0.161,0.4571,0.539,1],"ix":3},"o":{"a":0,"k":100,"ix":4},"w":{"a":0,"k":22,"ix":5},"lc":2,"lj":1,"ml":4,"bm":0,"d":[{"n":"d","nm":"dash","v":{"a":0,"k":204,"ix":1}},{"n":"g","nm":"gap","v":{"a":0,"k":307,"ix":2}},{"n":"o","nm":"offset","v":{"a":1,"k":[{"i":{"x":[0],"y":[1]},"o":{"x":[0.05],"y":[0]},"t":55.643,"s":[241]},{"t":79.7762532493533,"s":[98]}],"ix":7}}],"nm":"Stroke 1","mn":"ADBE Vector Graphic - Stroke","hd":false,"_render":true},{"ty":"tr","p":{"a":0,"k":[0,0],"ix":2},"a":{"a":0,"k":[0,0],"ix":1},"s":{"a":0,"k":[100,100],"ix":3},"r":{"a":0,"k":0,"ix":6},"o":{"a":0,"k":100,"ix":7},"sk":{"a":0,"k":0,"ix":4},"sa":{"a":0,"k":0,"ix":5},"nm":"Transform","_render":true}],"nm":"Shape 2","np":3,"cix":2,"bm":0,"ix":2,"mn":"ADBE Vector Group","hd":false,"_render":true},{"ty":"gr","it":[{"ind":0,"ty":"sh","ix":1,"ks":{"a":0,"k":{"i":[[-191.253,-38.043],[-121.977,-53.69]],"o":[[-191.253,-38.043],[-121.977,-53.69]],"v":[[-191.253,-38.043],[-121.977,-53.69]],"c":false},"ix":2},"nm":"Path 1","mn":"ADBE Vector Shape - Group","hd":false,"_render":true},{"ty":"st","c":{"a":0,"k":[0.161,0.4571,0.539,1],"ix":3},"o":{"a":0,"k":100,"ix":4},"w":{"a":0,"k":22,"ix":5},"lc":2,"lj":1,"ml":4,"bm":0,"d":[{"n":"d","nm":"dash","v":{"a":0,"k":204,"ix":1}},{"n":"g","nm":"gap","v":{"a":0,"k":307,"ix":2}},{"n":"o","nm":"offset","v":{"a":1,"k":[{"i":{"x":[0],"y":[1]},"o":{"x":[0.05],"y":[0]},"t":51.62,"s":[241]},{"t":75.7537530855135,"s":[98]}],"ix":7}}],"nm":"Stroke 1","mn":"ADBE Vector Graphic - Stroke","hd":false,"_render":true},{"ty":"tr","p":{"a":0,"k":[0,0],"ix":2},"a":{"a":0,"k":[0,0],"ix":1},"s":{"a":0,"k":[100,100],"ix":3},"r":{"a":0,"k":0,"ix":6},"o":{"a":0,"k":100,"ix":7},"sk":{"a":0,"k":0,"ix":4},"sa":{"a":0,"k":0,"ix":5},"nm":"Transform","_render":true}],"nm":"Shape 1","np":3,"cix":2,"bm":0,"ix":3,"mn":"ADBE Vector Group","hd":false,"_render":true},{"ty":"gr","it":[{"d":1,"ty":"el","s":{"a":0,"k":[101,101],"ix":2},"p":{"a":0,"k":[0,0],"ix":3},"nm":"Ellipse Path 1","mn":"ADBE Vector Shape - Ellipse","hd":false,"_render":true},{"ty":"fl","c":{"a":0,"k":[0.264,0.3984,0.936,1],"ix":4},"o":{"a":0,"k":100,"ix":5},"r":1,"bm":0,"nm":"Fill 1","mn":"ADBE Vector Graphic - Fill","hd":false,"_render":true},{"ty":"tr","p":{"a":0,"k":[0.274,-45.756],"ix":2},"a":{"a":0,"k":[0,0],"ix":1},"s":{"a":0,"k":[100,100],"ix":3},"r":{"a":0,"k":0,"ix":6},"o":{"a":0,"k":100,"ix":7},"sk":{"a":0,"k":0,"ix":4},"sa":{"a":0,"k":0,"ix":5},"nm":"Transform","_render":true}],"nm":"Ch hole","np":3,"cix":2,"bm":0,"ix":4,"mn":"ADBE Vector Group","hd":false,"_render":true},{"ty":"gr","it":[{"ind":0,"ty":"sh","ix":1,"ks":{"a":0,"k":{"i":[[61.887,-129.473],[-225.936,-59.951],[-209.583,70.052],[-156.308,58.878],[-137.742,95.581],[-111.665,50.719],[81.943,9.73]],"o":[[61.887,-129.473],[-225.936,-59.951],[-209.583,70.052],[-156.308,58.878],[-137.742,95.581],[-111.665,50.719],[81.943,9.73]],"v":[[61.887,-129.473],[-225.936,-59.951],[-209.583,70.052],[-156.308,58.878],[-137.742,95.581],[-111.665,50.719],[81.943,9.73]],"c":true},"ix":2},"nm":"Path 1","mn":"ADBE Vector Shape - Group","hd":false,"_render":true},{"ty":"fl","c":{"a":0,"k":[1,1,1,1],"ix":4},"o":{"a":0,"k":100,"ix":5},"r":1,"bm":0,"nm":"Fill 1","mn":"ADBE Vector Graphic - Fill","hd":false,"_render":true},{"ty":"tr","p":{"a":0,"k":[0,0],"ix":2},"a":{"a":0,"k":[0,0],"ix":1},"s":{"a":0,"k":[100,100],"ix":3},"r":{"a":0,"k":0,"ix":6},"o":{"a":0,"k":100,"ix":7},"sk":{"a":0,"k":0,"ix":4},"sa":{"a":0,"k":0,"ix":5},"nm":"Transform","_render":true}],"nm":"Body","np":3,"cix":2,"bm":0,"ix":6,"mn":"ADBE Vector Group","hd":false,"_render":true},{"ty":"gr","it":[{"ind":0,"ty":"sh","ix":1,"ks":{"a":0,"k":{"i":[[61.887,-129.473],[82.643,-112.367],[101.731,22.75],[-97.392,60.985],[-120.584,99.287],[-137.869,95.382],[-149.909,71.831],[-196.22,80.964],[-209.583,70.052],[-156.308,58.878],[-137.742,95.581],[-111.665,50.719],[81.943,9.73]],"o":[[61.887,-129.473],[82.643,-112.367],[101.731,22.75],[-97.392,60.985],[-120.584,99.287],[-137.869,95.382],[-149.909,71.831],[-196.22,80.964],[-209.583,70.052],[-156.308,58.878],[-137.742,95.581],[-111.665,50.719],[81.943,9.73]],"v":[[61.887,-129.473],[82.643,-112.367],[101.731,22.75],[-97.392,60.985],[-120.584,99.287],[-137.869,95.382],[-149.909,71.831],[-196.22,80.964],[-209.583,70.052],[-156.308,58.878],[-137.742,95.581],[-111.665,50.719],[81.943,9.73]],"c":true},"ix":2},"nm":"Path 1","mn":"ADBE Vector Shape - Group","hd":false,"_render":true},{"ty":"fl","c":{"a":0,"k":[0,0.1686,0.1686,1],"ix":4},"o":{"a":0,"k":100,"ix":5},"r":1,"bm":0,"nm":"Fill 1","mn":"ADBE Vector Graphic - Fill","hd":false,"_render":true},{"ty":"tr","p":{"a":0,"k":[0,0],"ix":2},"a":{"a":0,"k":[0,0],"ix":1},"s":{"a":0,"k":[100,100],"ix":3},"r":{"a":0,"k":0,"ix":6},"o":{"a":0,"k":100,"ix":7},"sk":{"a":0,"k":0,"ix":4},"sa":{"a":0,"k":0,"ix":5},"nm":"Transform","_render":true}],"nm":"Body 2","np":3,"cix":2,"bm":0,"ix":7,"mn":"ADBE Vector Group","hd":false,"_render":true}],"ip":0,"op":120.0000048877,"st":0,"bm":0,"completed":true},{"ddd":0,"ind":4,"ty":4,"nm":"L Ch Mask","parent":6,"td":1,"sr":1,"ks":{"o":{"a":0,"k":100,"ix":11},"r":{"a":0,"k":0,"ix":10},"p":{"a":0,"k":[0,0,0],"ix":2},"a":{"a":0,"k":[0,0,0],"ix":1},"s":{"a":0,"k":[100,100,100],"ix":6}},"ao":0,"shapes":[{"ty":"gr","it":[{"ind":0,"ty":"sh","ix":1,"ks":{"a":0,"k":{"i":[[-332.01300000000003,-206.617],[83.712,-29.296],[27.89,50.5],[-86.797,74.5]],"o":[[170.968,-380.104],[83.712,26.484],[-27.89,50.5],[-86.797,18.72]],"v":[[-72.066,-296.277],[83.712,-1.406],[0,50.5],[-86.797,46.61]],"c":true},"ix":2},"nm":"Path 1","mn":"ADBE Vector Shape - Group","hd":false,"_render":true},{"ty":"fl","c":{"a":0,"k":[0.264,0.3984,0.936,1],"ix":4},"o":{"a":0,"k":100,"ix":5},"r":1,"bm":0,"nm":"Fill 1","mn":"ADBE Vector Graphic - Fill","hd":false,"_render":true},{"ty":"tr","p":{"a":0,"k":[-147.974,-13.726],"ix":2},"a":{"a":0,"k":[0,0],"ix":1},"s":{"a":0,"k":[100,100],"ix":3},"r":{"a":0,"k":-12.868,"ix":6},"o":{"a":0,"k":100,"ix":7},"sk":{"a":0,"k":0,"ix":4},"sa":{"a":0,"k":0,"ix":5},"nm":"Transform","_render":true}],"nm":"Ch hole","np":3,"cix":2,"bm":0,"ix":1,"mn":"ADBE Vector Group","hd":false,"_render":true}],"ip":0,"op":120.0000048877,"st":0,"bm":0,"completed":true},{"ddd":0,"ind":5,"ty":4,"nm":"L Character","parent":4,"tt":1,"sr":1,"ks":{"o":{"a":1,"k":[{"i":{"x":[0.95],"y":[1]},"o":{"x":[1],"y":[0]},"t":99.889,"s":[100]},{"t":120.0000048877,"s":[0]}],"ix":11},"r":{"a":0,"k":-31,"ix":10},"p":{"a":0,"k":[-172.574,-49.772,0],"ix":2},"a":{"a":0,"k":[293.372,57,0],"ix":1},"s":{"a":0,"k":[100,100,100],"ix":6}},"ao":0,"shapes":[{"ty":"gr","it":[{"ty":"gr","it":[{"ind":0,"ty":"sh","ix":1,"ks":{"a":1,"k":[{"i":{"x":0,"y":1},"o":{"x":0.05,"y":0},"t":20.111,"s":[{"i":[[314,43.5],[316.23,89.81],[263.441,79.825]],"o":[[314,43.5],[316.23,89.81],[263.441,79.825]],"v":[[314,43.5],[316.23,89.81],[263.441,79.825]],"c":false}]},{"t":52.9612521571559,"s":[{"i":[[321,46.5],[317,109.5],[266,60]],"o":[[321,46.5],[317,109.5],[266,60]],"v":[[321,46.5],[317,109.5],[266,60]],"c":false}]}],"ix":2},"nm":"Path 2","mn":"ADBE Vector Shape - Group","hd":false,"_render":true},{"ty":"st","c":{"a":0,"k":[0.3118,0.4391,0.9482,1],"ix":3},"o":{"a":0,"k":100,"ix":4},"w":{"a":0,"k":40,"ix":5},"lc":1,"lj":2,"bm":0,"d":[{"n":"d","nm":"dash","v":{"a":0,"k":149,"ix":1}},{"n":"g","nm":"gap","v":{"a":0,"k":118,"ix":2}},{"n":"o","nm":"offset","v":{"a":0,"k":-236,"ix":7}}],"nm":"Shirt","mn":"ADBE Vector Graphic - Stroke","hd":false,"_render":true},{"ty":"st","c":{"a":0,"k":[0.3118,0.4391,0.9482,1],"ix":3},"o":{"a":0,"k":100,"ix":4},"w":{"a":0,"k":40,"ix":5},"lc":2,"lj":2,"bm":0,"d":[{"n":"d","nm":"dash","v":{"a":0,"k":149,"ix":1}},{"n":"g","nm":"gap","v":{"a":0,"k":118,"ix":2}},{"n":"o","nm":"offset","v":{"a":0,"k":-173,"ix":7}}],"nm":"Shirt 2","mn":"ADBE Vector Graphic - Stroke","hd":false,"_render":true},{"ty":"st","c":{"a":0,"k":[0.2456,0.3834,0.9344,1],"ix":3},"o":{"a":0,"k":100,"ix":4},"w":{"a":0,"k":33,"ix":5},"lc":2,"lj":2,"bm":0,"d":[{"n":"d","nm":"dash","v":{"a":0,"k":111,"ix":1}},{"n":"g","nm":"gap","v":{"a":0,"k":118,"ix":2}},{"n":"o","nm":"offset","v":{"a":0,"k":-43,"ix":7}}],"nm":"Skin","mn":"ADBE Vector Graphic - Stroke","hd":false,"_render":true},{"ty":"tr","p":{"a":0,"k":[0,0],"ix":2},"a":{"a":0,"k":[0,0],"ix":1},"s":{"a":0,"k":[100,100],"ix":3},"r":{"a":0,"k":0,"ix":6},"o":{"a":0,"k":100,"ix":7},"sk":{"a":0,"k":0,"ix":4},"sa":{"a":0,"k":0,"ix":5},"nm":"Transform","_render":true}],"nm":"L Hand","np":5,"cix":2,"bm":0,"ix":1,"mn":"ADBE Vector Group","hd":false,"_render":true},{"ty":"gr","it":[{"ty":"gr","it":[{"ind":0,"ty":"sh","ix":1,"ks":{"a":0,"k":{"i":[[194,-13],[198.375,-14.875],[216.549,-12.167],[225.359,32.503],[221.5,34.5],[213,-10]],"o":[[194,-13],[198.375,-14.875],[216.549,-12.167],[225.359,32.503],[221.5,34.5],[213,-10]],"v":[[194,-13],[198.375,-14.875],[216.549,-12.167],[225.359,32.503],[221.5,34.5],[213,-10]],"c":true},"ix":2},"nm":"Path 1","mn":"ADBE Vector Shape - Group","hd":false,"_render":true},{"ty":"fl","c":{"a":0,"k":[0,0.7765,1,1],"ix":4},"o":{"a":0,"k":100,"ix":5},"r":1,"bm":0,"nm":"Fill 1","mn":"ADBE Vector Graphic - Fill","hd":false,"_render":true},{"ty":"tr","p":{"a":0,"k":[0,0],"ix":2},"a":{"a":0,"k":[0,0],"ix":1},"s":{"a":0,"k":[100,100],"ix":3},"r":{"a":0,"k":0,"ix":6},"o":{"a":0,"k":100,"ix":7},"sk":{"a":0,"k":0,"ix":4},"sa":{"a":0,"k":0,"ix":5},"nm":"Transform","_render":true}],"nm":"Shape 5","np":3,"cix":2,"bm":0,"ix":1,"mn":"ADBE Vector Group","hd":false,"_render":true},{"ty":"gr","it":[{"ind":0,"ty":"sh","ix":1,"ks":{"a":0,"k":{"i":[[194,-13],[204,31],[221.5,34.5],[213,-10]],"o":[[194,-13],[204,31],[221.5,34.5],[213,-10]],"v":[[194,-13],[204,31],[221.5,34.5],[213,-10]],"c":true},"ix":2},"nm":"Path 1","mn":"ADBE Vector Shape - Group","hd":false,"_render":true},{"ty":"fl","c":{"a":0,"k":[0.161,0.4571,0.539,1],"ix":4},"o":{"a":0,"k":100,"ix":5},"r":1,"bm":0,"nm":"Fill 1","mn":"ADBE Vector Graphic - Fill","hd":false,"_render":true},{"ty":"tr","p":{"a":0,"k":[0,0],"ix":2},"a":{"a":0,"k":[0,0],"ix":1},"s":{"a":0,"k":[100,100],"ix":3},"r":{"a":0,"k":0,"ix":6},"o":{"a":0,"k":100,"ix":7},"sk":{"a":0,"k":0,"ix":4},"sa":{"a":0,"k":0,"ix":5},"nm":"Transform","_render":true}],"nm":"Shape 4","np":3,"cix":2,"bm":0,"ix":2,"mn":"ADBE Vector Group","hd":false,"_render":true},{"ty":"tr","p":{"a":1,"k":[{"i":{"x":0,"y":1},"o":{"x":0.245,"y":0},"t":20.111,"s":[258.786,73.168],"to":[2.013,2.587],"ti":[-1.149,4.976]},{"t":52.9612521571559,"s":[265.68,43.313]}],"ix":2},"a":{"a":0,"k":[209.68,9.813],"ix":1},"s":{"a":0,"k":[100,100],"ix":3},"r":{"a":0,"k":-17.407,"ix":6},"o":{"a":0,"k":100,"ix":7},"sk":{"a":0,"k":0,"ix":4},"sa":{"a":0,"k":0,"ix":5},"nm":"Transform","_render":true}],"nm":"Ph","np":3,"cix":2,"bm":0,"ix":2,"mn":"ADBE Vector Group","hd":false,"_render":true},{"ty":"gr","it":[{"ind":0,"ty":"sh","ix":1,"ks":{"a":0,"k":{"i":[[325.662,-79.955],[244.221,-64.863],[250.137,15.543],[283.162,-46.455],[299.662,-45.455],[323.876,23.906]],"o":[[268.662,-94.455],[227.662,0.5450000000000017],[254.662,-48.455],[283.162,-46.455],[305.662,11.545000000000002],[326.662,-42.955]],"v":[[295.162,-78.455],[237.662,-38.955],[251.162,1.045],[283.162,-46.455],[302.662,-16.955],[325.662,-18.955]],"c":true},"ix":2},"nm":"Path 1","mn":"ADBE Vector Shape - Group","hd":false,"_render":true},{"ty":"fl","c":{"a":0,"k":[0,0.1686,0.1686,1],"ix":4},"o":{"a":0,"k":100,"ix":5},"r":1,"bm":0,"nm":"Fill 1","mn":"ADBE Vector Graphic - Fill","hd":false,"_render":true},{"ty":"tr","p":{"a":0,"k":[0,0],"ix":2},"a":{"a":0,"k":[0,0],"ix":1},"s":{"a":0,"k":[100,100],"ix":3},"r":{"a":0,"k":0,"ix":6},"o":{"a":0,"k":100,"ix":7},"sk":{"a":0,"k":0,"ix":4},"sa":{"a":0,"k":0,"ix":5},"nm":"Transform","_render":true}],"nm":"Hair","np":3,"cix":2,"bm":0,"ix":4,"mn":"ADBE Vector Group","hd":false,"_render":true},{"ty":"gr","it":[{"ind":0,"ty":"sh","ix":1,"ks":{"a":0,"k":{"i":[[286,14],[280,-38]],"o":[[286,14],[280,-38]],"v":[[286,14],[280,-38]],"c":false},"ix":2},"nm":"Path 1","mn":"ADBE Vector Shape - Group","hd":false,"_render":true},{"ty":"st","c":{"a":0,"k":[0.2456,0.3834,0.9344,1],"ix":3},"o":{"a":0,"k":100,"ix":4},"w":{"a":0,"k":73,"ix":5},"lc":2,"lj":1,"ml":4,"bm":0,"d":[{"n":"d","nm":"dash","v":{"a":0,"k":39,"ix":1}},{"n":"g","nm":"gap","v":{"a":0,"k":99,"ix":2}},{"n":"o","nm":"offset","v":{"a":0,"k":-45,"ix":7}}],"nm":"Stroke 1","mn":"ADBE Vector Graphic - Stroke","hd":false,"_render":true},{"ty":"st","c":{"a":0,"k":[0.2456,0.3834,0.9344,1],"ix":3},"o":{"a":0,"k":100,"ix":4},"w":{"a":0,"k":33,"ix":5},"lc":2,"lj":1,"ml":4,"bm":0,"nm":"Stroke 2","mn":"ADBE Vector Graphic - Stroke","hd":false,"_render":true},{"ty":"tr","p":{"a":0,"k":[0,0],"ix":2},"a":{"a":0,"k":[0,0],"ix":1},"s":{"a":0,"k":[100,100],"ix":3},"r":{"a":0,"k":0,"ix":6},"o":{"a":0,"k":100,"ix":7},"sk":{"a":0,"k":0,"ix":4},"sa":{"a":0,"k":0,"ix":5},"nm":"Transform","_render":true}],"nm":"Face","np":4,"cix":2,"bm":0,"ix":5,"mn":"ADBE Vector Group","hd":false,"_render":true},{"ty":"gr","it":[{"ind":0,"ty":"sh","ix":1,"ks":{"a":0,"k":{"i":[[347.62,-4.872],[244,94],[266,152],[343,136]],"o":[[226,14],[254,134],[320,152],[345,94]],"v":[[284,5],[249,114],[293,152],[344,115]],"c":true},"ix":2},"nm":"Path 1","mn":"ADBE Vector Shape - Group","hd":false,"_render":true},{"ty":"fl","c":{"a":0,"k":[0.38,0.504,1,1],"ix":4},"o":{"a":0,"k":100,"ix":5},"r":1,"bm":0,"nm":"Fill 1","mn":"ADBE Vector Graphic - Fill","hd":false,"_render":true},{"ty":"tr","p":{"a":0,"k":[0,0],"ix":2},"a":{"a":0,"k":[0,0],"ix":1},"s":{"a":0,"k":[100,100],"ix":3},"r":{"a":0,"k":0,"ix":6},"o":{"a":0,"k":100,"ix":7},"sk":{"a":0,"k":0,"ix":4},"sa":{"a":0,"k":0,"ix":5},"nm":"Transform","_render":true}],"nm":"Body","np":3,"cix":2,"bm":0,"ix":6,"mn":"ADBE Vector Group","hd":false,"_render":true},{"ty":"gr","it":[{"ind":0,"ty":"sh","ix":1,"ks":{"a":1,"k":[{"i":{"x":0,"y":1},"o":{"x":0.05,"y":0},"t":20.783,"s":[{"i":[[263,38],[237.401,78.281],[258.547,113.032]],"o":[[263,38],[237.401,78.281],[258.547,113.032]],"v":[[263,38],[237.401,78.281],[258.547,113.032]],"c":false}]},{"t":53.6312521844456,"s":[{"i":[[263,38],[246.255,82.31],[234.834,119.341]],"o":[[263,38],[246.255,82.31],[234.834,119.341]],"v":[[263,38],[246.255,82.31],[234.834,119.341]],"c":false}]}],"ix":2},"nm":"Path 1","mn":"ADBE Vector Shape - Group","hd":false,"_render":true},{"ty":"st","c":{"a":0,"k":[0.3118,0.4391,0.9482,1],"ix":3},"o":{"a":0,"k":100,"ix":4},"w":{"a":0,"k":40,"ix":5},"lc":1,"lj":2,"bm":0,"d":[{"n":"d","nm":"dash","v":{"a":0,"k":149,"ix":1}},{"n":"g","nm":"gap","v":{"a":0,"k":118,"ix":2}},{"n":"o","nm":"offset","v":{"a":0,"k":-236,"ix":7}}],"nm":"Shirt","mn":"ADBE Vector Graphic - Stroke","hd":false,"_render":true},{"ty":"st","c":{"a":0,"k":[0.3118,0.4391,0.9482,1],"ix":3},"o":{"a":0,"k":100,"ix":4},"w":{"a":0,"k":40,"ix":5},"lc":2,"lj":2,"bm":0,"d":[{"n":"d","nm":"dash","v":{"a":0,"k":149,"ix":1}},{"n":"g","nm":"gap","v":{"a":0,"k":118,"ix":2}},{"n":"o","nm":"offset","v":{"a":0,"k":-173,"ix":7}}],"nm":"Shirt 2","mn":"ADBE Vector Graphic - Stroke","hd":false,"_render":true},{"ty":"st","c":{"a":0,"k":[0.2456,0.3834,0.9344,1],"ix":3},"o":{"a":0,"k":100,"ix":4},"w":{"a":0,"k":33,"ix":5},"lc":2,"lj":2,"bm":0,"d":[{"n":"d","nm":"dash","v":{"a":0,"k":111,"ix":1}},{"n":"g","nm":"gap","v":{"a":0,"k":118,"ix":2}},{"n":"o","nm":"offset","v":{"a":0,"k":-43,"ix":7}}],"nm":"Skin","mn":"ADBE Vector Graphic - Stroke","hd":false,"_render":true},{"ty":"tr","p":{"a":0,"k":[0,0],"ix":2},"a":{"a":0,"k":[0,0],"ix":1},"s":{"a":0,"k":[100,100],"ix":3},"r":{"a":0,"k":0,"ix":6},"o":{"a":0,"k":100,"ix":7},"sk":{"a":0,"k":0,"ix":4},"sa":{"a":0,"k":0,"ix":5},"nm":"Transform","_render":true}],"nm":"R hand","np":5,"cix":2,"bm":0,"ix":7,"mn":"ADBE Vector Group","hd":false,"_render":true},{"ty":"tr","p":{"a":0,"k":[303.165,131.637],"ix":2},"a":{"a":0,"k":[303.165,131.637],"ix":1},"s":{"a":1,"k":[{"i":{"x":[0,0],"y":[1,1]},"o":{"x":[0.05,0.05],"y":[0,0]},"t":9.385,"s":[0,0]},{"t":29.4975012014578,"s":[100,100]}],"ix":3},"r":{"a":1,"k":[{"i":{"x":[0],"y":[1]},"o":{"x":[0.05],"y":[0]},"t":9.385,"s":[26]},{"t":29.4975012014578,"s":[0]}],"ix":6},"o":{"a":0,"k":100,"ix":7},"sk":{"a":0,"k":0,"ix":4},"sa":{"a":0,"k":0,"ix":5},"nm":"Transform","_render":true}],"nm":"Group 1","np":7,"cix":2,"bm":0,"ix":1,"mn":"ADBE Vector Group","hd":false,"_render":true}],"ip":0,"op":120.0000048877,"st":0,"bm":0,"completed":true},{"ddd":0,"ind":6,"ty":4,"nm":"L Chat Box","parent":9,"sr":1,"ks":{"o":{"a":1,"k":[{"i":{"x":[0.95],"y":[1]},"o":{"x":[1],"y":[0]},"t":103.91,"s":[100]},{"t":120.0000048877,"s":[0]}],"ix":11},"r":{"a":1,"k":[{"i":{"x":[0],"y":[1]},"o":{"x":[0.05],"y":[0]},"t":0,"s":[28]},{"t":40.2237516383469,"s":[-31]}],"ix":10},"p":{"a":1,"k":[{"i":{"x":0,"y":1},"o":{"x":0.05,"y":0},"t":40.224,"s":[381.75,501.25,0],"to":[15.167,67.167,0],"ti":[-15.167,-67.167,0]},{"t":120.0000048877,"s":[472.75,904.25,0]}],"ix":2},"a":{"a":0,"k":[-132.173,82.917,0],"ix":1},"s":{"a":1,"k":[{"i":{"x":[0,0,0],"y":[1,1,1]},"o":{"x":[0.05,0.05,0.05],"y":[0,0,0]},"t":0,"s":[0,0,100]},{"t":40.2237516383469,"s":[-100,100,100]}],"ix":6}},"ao":0,"shapes":[{"ty":"gr","it":[{"ind":0,"ty":"sh","ix":1,"ks":{"a":0,"k":{"i":[[44.465,-43.061],[-8.863,-30.851]],"o":[[44.465,-43.061],[-8.863,-30.851]],"v":[[44.465,-43.061],[-8.863,-30.851]],"c":false},"ix":2},"nm":"Path 1","mn":"ADBE Vector Shape - Group","hd":false,"_render":true},{"ty":"st","c":{"a":0,"k":[0.1517,0.4937,0.5883,1],"ix":3},"o":{"a":0,"k":100,"ix":4},"w":{"a":0,"k":20,"ix":5},"lc":2,"lj":1,"ml":4,"bm":0,"d":[{"n":"d","nm":"dash","v":{"a":0,"k":156,"ix":1}},{"n":"g","nm":"gap","v":{"a":0,"k":262,"ix":2}},{"n":"o","nm":"offset","v":{"a":1,"k":[{"i":{"x":[0],"y":[1]},"o":{"x":[0.05],"y":[0]},"t":61.005,"s":[230]},{"t":84.4687534404827,"s":[31]}],"ix":7}}],"nm":"Stroke 1","mn":"ADBE Vector Graphic - Stroke","hd":false,"_render":true},{"ty":"tr","p":{"a":0,"k":[0,0],"ix":2},"a":{"a":0,"k":[0,0],"ix":1},"s":{"a":0,"k":[100,100],"ix":3},"r":{"a":0,"k":0,"ix":6},"o":{"a":0,"k":100,"ix":7},"sk":{"a":0,"k":0,"ix":4},"sa":{"a":0,"k":0,"ix":5},"nm":"Transform","_render":true}],"nm":"Shape 3","np":3,"cix":2,"bm":0,"ix":1,"mn":"ADBE Vector Group","hd":false,"_render":true},{"ty":"gr","it":[{"ind":0,"ty":"sh","ix":1,"ks":{"a":0,"k":{"i":[[41.018,-70.156],[-49.176,-47.461]],"o":[[41.018,-70.156],[-49.176,-47.461]],"v":[[41.018,-70.156],[-49.176,-47.461]],"c":false},"ix":2},"nm":"Path 1","mn":"ADBE Vector Shape - Group","hd":false,"_render":true},{"ty":"st","c":{"a":0,"k":[0.1517,0.4937,0.5883,1],"ix":3},"o":{"a":0,"k":100,"ix":4},"w":{"a":0,"k":20,"ix":5},"lc":2,"lj":1,"ml":4,"bm":0,"d":[{"n":"d","nm":"dash","v":{"a":0,"k":156,"ix":1}},{"n":"g","nm":"gap","v":{"a":0,"k":262,"ix":2}},{"n":"o","nm":"offset","v":{"a":1,"k":[{"i":{"x":[0],"y":[1]},"o":{"x":[0.05],"y":[0]},"t":50.95,"s":[230]},{"t":74.4137530309342,"s":[31]}],"ix":7}}],"nm":"Stroke 1","mn":"ADBE Vector Graphic - Stroke","hd":false,"_render":true},{"ty":"tr","p":{"a":0,"k":[0,0],"ix":2},"a":{"a":0,"k":[0,0],"ix":1},"s":{"a":0,"k":[100,100],"ix":3},"r":{"a":0,"k":0,"ix":6},"o":{"a":0,"k":100,"ix":7},"sk":{"a":0,"k":0,"ix":4},"sa":{"a":0,"k":0,"ix":5},"nm":"Transform","_render":true}],"nm":"Shape 2","np":3,"cix":2,"bm":0,"ix":2,"mn":"ADBE Vector Group","hd":false,"_render":true},{"ty":"gr","it":[{"ind":0,"ty":"sh","ix":1,"ks":{"a":0,"k":{"i":[[35.857,-96.22],[-75.943,-68.71]],"o":[[35.857,-96.22],[-75.943,-68.71]],"v":[[35.857,-96.22],[-75.943,-68.71]],"c":false},"ix":2},"nm":"Path 1","mn":"ADBE Vector Shape - Group","hd":false,"_render":true},{"ty":"st","c":{"a":0,"k":[0.1517,0.4937,0.5883,1],"ix":3},"o":{"a":0,"k":100,"ix":4},"w":{"a":0,"k":20,"ix":5},"lc":2,"lj":1,"ml":4,"bm":0,"d":[{"n":"d","nm":"dash","v":{"a":0,"k":156,"ix":1}},{"n":"g","nm":"gap","v":{"a":0,"k":262,"ix":2}},{"n":"o","nm":"offset","v":{"a":1,"k":[{"i":{"x":[0],"y":[1]},"o":{"x":[0.05],"y":[0]},"t":39.553,"s":[230]},{"t":62.3462525394148,"s":[31]}],"ix":7}}],"nm":"Stroke 1","mn":"ADBE Vector Graphic - Stroke","hd":false,"_render":true},{"ty":"tr","p":{"a":0,"k":[0,0],"ix":2},"a":{"a":0,"k":[0,0],"ix":1},"s":{"a":0,"k":[100,100],"ix":3},"r":{"a":0,"k":0,"ix":6},"o":{"a":0,"k":100,"ix":7},"sk":{"a":0,"k":0,"ix":4},"sa":{"a":0,"k":0,"ix":5},"nm":"Transform","_render":true}],"nm":"Shape 1","np":3,"cix":2,"bm":0,"ix":3,"mn":"ADBE Vector Group","hd":false,"_render":true},{"ty":"gr","it":[{"d":1,"ty":"el","s":{"a":0,"k":[101,101],"ix":2},"p":{"a":0,"k":[0,0],"ix":3},"nm":"Ellipse Path 1","mn":"ADBE Vector Shape - Ellipse","hd":false,"_render":true},{"ty":"fl","c":{"a":0,"k":[0.264,0.3984,0.936,1],"ix":4},"o":{"a":0,"k":100,"ix":5},"r":1,"bm":0,"nm":"Fill 1","mn":"ADBE Vector Graphic - Fill","hd":false,"_render":true},{"ty":"tr","p":{"a":0,"k":[-147.974,-13.726],"ix":2},"a":{"a":0,"k":[0,0],"ix":1},"s":{"a":0,"k":[100,100],"ix":3},"r":{"a":0,"k":-12.868,"ix":6},"o":{"a":0,"k":100,"ix":7},"sk":{"a":0,"k":0,"ix":4},"sa":{"a":0,"k":0,"ix":5},"nm":"Transform","_render":true}],"nm":"Ch hole","np":3,"cix":2,"bm":0,"ix":5,"mn":"ADBE Vector Group","hd":false,"_render":true},{"ty":"gr","it":[{"ty":"gr","it":[{"ind":0,"ty":"sh","ix":1,"ks":{"a":0,"k":{"i":[[61.887,-129.473],[-225.936,-59.951],[-209.583,70.052],[-156.308,58.878],[-137.742,95.581],[-111.665,50.719],[81.943,9.73]],"o":[[61.887,-129.473],[-225.936,-59.951],[-209.583,70.052],[-156.308,58.878],[-137.742,95.581],[-111.665,50.719],[81.943,9.73]],"v":[[61.887,-129.473],[-225.936,-59.951],[-209.583,70.052],[-156.308,58.878],[-137.742,95.581],[-111.665,50.719],[81.943,9.73]],"c":true},"ix":2},"nm":"Path 1","mn":"ADBE Vector Shape - Group","hd":false,"_render":true},{"ty":"fl","c":{"a":0,"k":[1,1,1,1],"ix":4},"o":{"a":0,"k":100,"ix":5},"r":1,"bm":0,"nm":"Fill 1","mn":"ADBE Vector Graphic - Fill","hd":false,"_render":true},{"ty":"tr","p":{"a":0,"k":[0,0],"ix":2},"a":{"a":0,"k":[0,0],"ix":1},"s":{"a":0,"k":[100,100],"ix":3},"r":{"a":0,"k":0,"ix":6},"o":{"a":0,"k":100,"ix":7},"sk":{"a":0,"k":0,"ix":4},"sa":{"a":0,"k":0,"ix":5},"nm":"Transform","_render":true}],"nm":"Body","np":3,"cix":2,"bm":0,"ix":1,"mn":"ADBE Vector Group","hd":false,"_render":true},{"ty":"gr","it":[{"ind":0,"ty":"sh","ix":1,"ks":{"a":0,"k":{"i":[[61.887,-129.473],[82.643,-112.367],[101.731,22.75],[-97.392,60.985],[-120.584,99.287],[-137.869,95.382],[-149.909,71.831],[-196.22,80.964],[-209.583,70.052],[-156.308,58.878],[-137.742,95.581],[-111.665,50.719],[81.943,9.73]],"o":[[61.887,-129.473],[82.643,-112.367],[101.731,22.75],[-97.392,60.985],[-120.584,99.287],[-137.869,95.382],[-149.909,71.831],[-196.22,80.964],[-209.583,70.052],[-156.308,58.878],[-137.742,95.581],[-111.665,50.719],[81.943,9.73]],"v":[[61.887,-129.473],[82.643,-112.367],[101.731,22.75],[-97.392,60.985],[-120.584,99.287],[-137.869,95.382],[-149.909,71.831],[-196.22,80.964],[-209.583,70.052],[-156.308,58.878],[-137.742,95.581],[-111.665,50.719],[81.943,9.73]],"c":true},"ix":2},"nm":"Path 1","mn":"ADBE Vector Shape - Group","hd":false,"_render":true},{"ty":"fl","c":{"a":0,"k":[0,0.1686,0.1686,1],"ix":4},"o":{"a":0,"k":100,"ix":5},"r":1,"bm":0,"nm":"Fill 1","mn":"ADBE Vector Graphic - Fill","hd":false,"_render":true},{"ty":"tr","p":{"a":0,"k":[0,0],"ix":2},"a":{"a":0,"k":[0,0],"ix":1},"s":{"a":0,"k":[100,100],"ix":3},"r":{"a":0,"k":0,"ix":6},"o":{"a":0,"k":100,"ix":7},"sk":{"a":0,"k":0,"ix":4},"sa":{"a":0,"k":0,"ix":5},"nm":"Transform","_render":true}],"nm":"Body Shadow","np":3,"cix":2,"bm":0,"ix":2,"mn":"ADBE Vector Group","hd":false,"_render":true},{"ty":"tr","p":{"a":0,"k":[-62.103,-15.093],"ix":2},"a":{"a":0,"k":[-62.103,-15.093],"ix":1},"s":{"a":0,"k":[100,100],"ix":3},"r":{"a":0,"k":0,"ix":6},"o":{"a":0,"k":100,"ix":7},"sk":{"a":0,"k":0,"ix":4},"sa":{"a":0,"k":0,"ix":5},"nm":"Transform","_render":true}],"nm":"Chat Body","np":2,"cix":2,"bm":0,"ix":6,"mn":"ADBE Vector Group","hd":false,"_render":true}],"ip":0,"op":120.0000048877,"st":0,"bm":0,"completed":true},{"ddd":0,"ind":7,"ty":4,"nm":"Phone Mask","td":1,"sr":1,"ks":{"o":{"a":0,"k":100,"ix":11},"r":{"a":0,"k":0,"ix":10},"p":{"a":1,"k":[{"i":{"x":0,"y":1},"o":{"x":0.05,"y":0},"t":0,"s":[567.419,615.585,0],"to":null,"ti":null},{"i":{"x":0,"y":1},"o":{"x":0.05,"y":0},"t":90,"s":[557.419,580.585,0],"to":null,"ti":null},{"t":119.000004846969,"s":[567.419,615.585,0]}],"ix":2},"a":{"a":0,"k":[502.169,598.835,0],"ix":1},"s":{"a":1,"k":[{"i":{"x":[0,0,0],"y":[1,1,1]},"o":{"x":[0.05,0.05,0.05],"y":[0,0,0]},"t":0,"s":[80,80,100]},{"i":{"x":[0,0,0],"y":[1,1,1]},"o":{"x":[0.05,0.05,0.05],"y":[0,0,0]},"t":90,"s":[110,110,100]},{"t":119.000004846969,"s":[80,80,100]}],"ix":6}},"ao":0,"shapes":[{"ty":"gr","it":[{"ty":"gr","it":[{"ind":0,"ty":"sh","ix":1,"ks":{"a":0,"k":{"i":[[-201,-376],[-500,-276],[-350,375],[-75,250]],"o":[[-201,-376],[-500,-276],[-350,375],[-75,250]],"v":[[-201,-376],[-500,-276],[-350,375],[-75,250]],"c":true},"ix":2},"nm":"Path 1","mn":"ADBE Vector Shape - Group","hd":false,"_render":true},{"ty":"rd","nm":"Round Corners 1","r":{"a":0,"k":40,"ix":1},"ix":2,"mn":"ADBE Vector Filter - RC","hd":false,"_render":true},{"ty":"st","c":{"a":0,"k":[0.1517,0.4937,0.5883,1],"ix":3},"o":{"a":0,"k":100,"ix":4},"w":{"a":0,"k":2,"ix":5},"lc":1,"lj":1,"ml":4,"bm":0,"nm":"Stroke 1","mn":"ADBE Vector Graphic - Stroke","hd":false,"_render":true},{"ty":"fl","c":{"a":0,"k":[0.5725,0.6549,0.9961,1],"ix":4},"o":{"a":0,"k":100,"ix":5},"r":1,"bm":0,"nm":"Fill 1","mn":"ADBE Vector Graphic - Fill","hd":false,"_render":true},{"ty":"tr","p":{"a":0,"k":[0,0],"ix":2},"a":{"a":0,"k":[0,0],"ix":1},"s":{"a":0,"k":[100,100],"ix":3},"r":{"a":0,"k":0,"ix":6},"o":{"a":0,"k":100,"ix":7},"sk":{"a":0,"k":0,"ix":4},"sa":{"a":0,"k":0,"ix":5},"nm":"Transform","_render":true}],"nm":"Shape 1","np":4,"cix":2,"bm":0,"ix":1,"mn":"ADBE Vector Group","hd":false,"_render":true},{"ty":"tr","p":{"a":0,"k":[800,600],"ix":2},"a":{"a":0,"k":[0,0],"ix":1},"s":{"a":0,"k":[100,100],"ix":3},"r":{"a":0,"k":0,"ix":6},"o":{"a":0,"k":100,"ix":7},"sk":{"a":0,"k":0,"ix":4},"sa":{"a":0,"k":0,"ix":5},"nm":"Transform","_render":true}],"nm":"Screen F","np":1,"cix":2,"bm":0,"ix":1,"mn":"ADBE Vector Group","hd":false,"_render":true}],"ip":0,"op":120.0000048877,"st":0,"bm":0,"completed":true},{"ddd":0,"ind":8,"ty":4,"nm":"Light","parent":7,"tt":1,"sr":1,"ks":{"o":{"a":0,"k":100,"ix":11},"r":{"a":0,"k":0,"ix":10},"p":{"a":0,"k":[546.645,650.604,0],"ix":2},"a":{"a":0,"k":[0,0,0],"ix":1},"s":{"a":0,"k":[125,125,100],"ix":6}},"ao":0,"shapes":[{"ty":"gr","it":[{"ind":0,"ty":"sh","ix":1,"ks":{"a":1,"k":[{"i":{"x":0,"y":1},"o":{"x":0.05,"y":0},"t":5,"s":[{"i":[[304,36],[-176,544],[-152,568],[320,100]],"o":[[304,36],[-176,544],[-152,568],[320,100]],"v":[[304,36],[-176,544],[-152,568],[320,100]],"c":true}]},{"i":{"x":0,"y":1},"o":{"x":0.167,"y":0},"t":43,"s":[{"i":[[28,-684],[-544,-408],[-532,-392],[32,-636]],"o":[[28,-684],[-544,-408],[-532,-392],[32,-636]],"v":[[28,-684],[-544,-408],[-532,-392],[32,-636]],"c":true}]},{"i":{"x":0.833,"y":1},"o":{"x":0.167,"y":0},"t":93,"s":[{"i":[[28,-684],[-544,-408],[-532,-392],[32,-636]],"o":[[28,-684],[-544,-408],[-532,-392],[32,-636]],"v":[[28,-684],[-544,-408],[-532,-392],[32,-636]],"c":true}]},{"t":115.000004684046,"s":[{"i":[[304,36],[-176,544],[-152,568],[320,100]],"o":[[304,36],[-176,544],[-152,568],[320,100]],"v":[[304,36],[-176,544],[-152,568],[320,100]],"c":true}]}],"ix":2},"nm":"Path 1","mn":"ADBE Vector Shape - Group","hd":false,"_render":true},{"ty":"fl","c":{"a":0,"k":[1,1,1,1],"ix":4},"o":{"a":0,"k":100,"ix":5},"r":1,"bm":0,"nm":"Fill 1","mn":"ADBE Vector Graphic - Fill","hd":false,"_render":true},{"ty":"tr","p":{"a":0,"k":[0,0],"ix":2},"a":{"a":0,"k":[0,0],"ix":1},"s":{"a":0,"k":[100,100],"ix":3},"r":{"a":0,"k":0,"ix":6},"o":{"a":0,"k":100,"ix":7},"sk":{"a":0,"k":0,"ix":4},"sa":{"a":0,"k":0,"ix":5},"nm":"Transform","_render":true}],"nm":"Shape 2","np":3,"cix":2,"bm":0,"ix":1,"mn":"ADBE Vector Group","hd":false,"_render":true},{"ty":"gr","it":[{"ind":0,"ty":"sh","ix":1,"ks":{"a":1,"k":[{"i":{"x":0,"y":1},"o":{"x":0.05,"y":0},"t":1,"s":[{"i":[[304,36],[-176,544],[-152,568],[320,100]],"o":[[304,36],[-176,544],[-152,568],[320,100]],"v":[[304,36],[-176,544],[-152,568],[320,100]],"c":true}]},{"i":{"x":0,"y":1},"o":{"x":0.167,"y":0},"t":39,"s":[{"i":[[28,-684],[-544,-408],[-532,-392],[32,-636]],"o":[[28,-684],[-544,-408],[-532,-392],[32,-636]],"v":[[28,-684],[-544,-408],[-532,-392],[32,-636]],"c":true}]},{"i":{"x":0.833,"y":1},"o":{"x":0.167,"y":0},"t":91,"s":[{"i":[[28,-684],[-544,-408],[-532,-392],[32,-636]],"o":[[28,-684],[-544,-408],[-532,-392],[32,-636]],"v":[[28,-684],[-544,-408],[-532,-392],[32,-636]],"c":true}]},{"t":113.000004602584,"s":[{"i":[[304,36],[-176,544],[-152,568],[320,100]],"o":[[304,36],[-176,544],[-152,568],[320,100]],"v":[[304,36],[-176,544],[-152,568],[320,100]],"c":true}]}],"ix":2},"nm":"Path 1","mn":"ADBE Vector Shape - Group","hd":false,"_render":true},{"ty":"fl","c":{"a":0,"k":[1,1,1,1],"ix":4},"o":{"a":0,"k":100,"ix":5},"r":1,"bm":0,"nm":"Fill 1","mn":"ADBE Vector Graphic - Fill","hd":false,"_render":true},{"ty":"tr","p":{"a":0,"k":[0,0],"ix":2},"a":{"a":0,"k":[0,0],"ix":1},"s":{"a":0,"k":[100,100],"ix":3},"r":{"a":0,"k":0,"ix":6},"o":{"a":0,"k":100,"ix":7},"sk":{"a":0,"k":0,"ix":4},"sa":{"a":0,"k":0,"ix":5},"nm":"Transform","_render":true}],"nm":"Shape 1","np":3,"cix":2,"bm":0,"ix":2,"mn":"ADBE Vector Group","hd":false,"_render":true}],"ip":0,"op":120.0000048877,"st":0,"bm":0,"completed":true},{"ddd":0,"ind":9,"ty":4,"nm":"Phone","sr":1,"ks":{"o":{"a":0,"k":100,"ix":11},"r":{"a":0,"k":0,"ix":10},"p":{"a":1,"k":[{"i":{"x":0,"y":1},"o":{"x":0.05,"y":0},"t":0,"s":[567.419,615.585,0],"to":null,"ti":null},{"i":{"x":0,"y":1},"o":{"x":0.05,"y":0},"t":90,"s":[557.419,580.585,0],"to":null,"ti":null},{"t":119.000004846969,"s":[567.419,615.585,0]}],"ix":2},"a":{"a":0,"k":[502.169,598.835,0],"ix":1},"s":{"a":1,"k":[{"i":{"x":[0,0,0],"y":[1,1,1]},"o":{"x":[0.05,0.05,0.05],"y":[0,0,0]},"t":0,"s":[80,80,100]},{"i":{"x":[0,0,0],"y":[1,1,1]},"o":{"x":[0.05,0.05,0.05],"y":[0,0,0]},"t":90,"s":[110,110,100]},{"t":119.000004846969,"s":[80,80,100]}],"ix":6}},"ao":0,"shapes":[{"ty":"gr","it":[{"ty":"gr","it":[{"ind":0,"ty":"sh","ix":1,"ks":{"a":0,"k":{"i":[[-201,-376],[-500,-276],[-350,375],[-75,250]],"o":[[-201,-376],[-500,-276],[-350,375],[-75,250]],"v":[[-201,-376],[-500,-276],[-350,375],[-75,250]],"c":true},"ix":2},"nm":"Path 1","mn":"ADBE Vector Shape - Group","hd":false,"_render":true},{"ty":"rd","nm":"Round Corners 1","r":{"a":0,"k":40,"ix":1},"ix":2,"mn":"ADBE Vector Filter - RC","hd":false,"_render":true},{"ty":"st","c":{"a":0,"k":[0.1517,0.4937,0.5883,1],"ix":3},"o":{"a":0,"k":100,"ix":4},"w":{"a":0,"k":2,"ix":5},"lc":1,"lj":1,"ml":4,"bm":0,"nm":"Stroke 1","mn":"ADBE Vector Graphic - Stroke","hd":false,"_render":true},{"ty":"fl","c":{"a":0,"k":[0.5725,0.6549,0.9961,1],"ix":4},"o":{"a":0,"k":100,"ix":5},"r":1,"bm":0,"nm":"Fill 1","mn":"ADBE Vector Graphic - Fill","hd":false,"_render":true},{"ty":"tr","p":{"a":0,"k":[0,0],"ix":2},"a":{"a":0,"k":[0,0],"ix":1},"s":{"a":0,"k":[100,100],"ix":3},"r":{"a":0,"k":0,"ix":6},"o":{"a":0,"k":100,"ix":7},"sk":{"a":0,"k":0,"ix":4},"sa":{"a":0,"k":0,"ix":5},"nm":"Transform","_render":true}],"nm":"Shape 1","np":4,"cix":2,"bm":0,"ix":1,"mn":"ADBE Vector Group","hd":false,"_render":true},{"ty":"tr","p":{"a":0,"k":[800,600],"ix":2},"a":{"a":0,"k":[0,0],"ix":1},"s":{"a":0,"k":[100,100],"ix":3},"r":{"a":0,"k":0,"ix":6},"o":{"a":0,"k":100,"ix":7},"sk":{"a":0,"k":0,"ix":4},"sa":{"a":0,"k":0,"ix":5},"nm":"Transform","_render":true}],"nm":"Screen F","np":1,"cix":2,"bm":0,"ix":1,"mn":"ADBE Vector Group","hd":false,"_render":true},{"ty":"gr","it":[{"ty":"gr","it":[{"ind":0,"ty":"sh","ix":1,"ks":{"a":0,"k":{"i":[[-445.5,-159.5],[-435.5,-115.5]],"o":[[-445.5,-159.5],[-435.5,-115.5]],"v":[[-445.5,-159.5],[-435.5,-115.5]],"c":false},"ix":2},"nm":"Path 1","mn":"ADBE Vector Shape - Group","hd":false,"_render":true},{"ind":1,"ty":"sh","ix":2,"ks":{"a":0,"k":{"i":[[-432,-99.5],[-423.5,-62]],"o":[[-432,-99.5],[-423.5,-62]],"v":[[-432,-99.5],[-423.5,-62]],"c":false},"ix":2},"nm":"Path 2","mn":"ADBE Vector Shape - Group","hd":false,"_render":true},{"ty":"st","c":{"a":0,"k":[0.5725,0.6549,0.9961,1],"ix":3},"o":{"a":0,"k":100,"ix":4},"w":{"a":0,"k":10,"ix":5},"lc":2,"lj":1,"ml":4,"bm":0,"nm":"Stroke 1","mn":"ADBE Vector Graphic - Stroke","hd":false,"_render":true},{"ty":"tr","p":{"a":0,"k":[0,0],"ix":2},"a":{"a":0,"k":[0,0],"ix":1},"s":{"a":0,"k":[100,100],"ix":3},"r":{"a":0,"k":0,"ix":6},"o":{"a":0,"k":100,"ix":7},"sk":{"a":0,"k":0,"ix":4},"sa":{"a":0,"k":0,"ix":5},"nm":"Transform","_render":true}],"nm":"Shape 2","np":4,"cix":2,"bm":0,"ix":1,"mn":"ADBE Vector Group","hd":false,"_render":true},{"ty":"gr","it":[{"ind":0,"ty":"sh","ix":1,"ks":{"a":0,"k":{"i":[[-163,-383.5],[-484,-282],[-332,383],[-76,268]],"o":[[-163,-383.5],[-484,-282],[-332,383],[-76,268]],"v":[[-163,-383.5],[-484,-282],[-332,383],[-76,268]],"c":true},"ix":2},"nm":"Path 1","mn":"ADBE Vector Shape - Group","hd":false,"_render":true},{"ty":"rd","nm":"Round Corners 1","r":{"a":0,"k":40,"ix":1},"ix":2,"mn":"ADBE Vector Filter - RC","hd":false,"_render":true},{"ty":"fl","c":{"a":0,"k":[0.1517,0.4937,0.5883,1],"ix":4},"o":{"a":0,"k":100,"ix":5},"r":1,"bm":0,"nm":"Fill 1","mn":"ADBE Vector Graphic - Fill","hd":false,"_render":true},{"ty":"tr","p":{"a":0,"k":[0,0],"ix":2},"a":{"a":0,"k":[0,0],"ix":1},"s":{"a":0,"k":[100,100],"ix":3},"r":{"a":0,"k":0,"ix":6},"o":{"a":0,"k":100,"ix":7},"sk":{"a":0,"k":0,"ix":4},"sa":{"a":0,"k":0,"ix":5},"nm":"Transform","_render":true}],"nm":"Shape 1","np":4,"cix":2,"bm":0,"ix":2,"mn":"ADBE Vector Group","hd":false,"_render":true},{"ty":"tr","p":{"a":0,"k":[762.5,600.5],"ix":2},"a":{"a":0,"k":[0,0],"ix":1},"s":{"a":0,"k":[100,100],"ix":3},"r":{"a":0,"k":0,"ix":6},"o":{"a":0,"k":100,"ix":7},"sk":{"a":0,"k":0,"ix":4},"sa":{"a":0,"k":0,"ix":5},"nm":"Transform","_render":true}],"nm":"Screen B","np":2,"cix":2,"bm":0,"ix":2,"mn":"ADBE Vector Group","hd":false,"_render":true}],"ip":0,"op":120.0000048877,"st":0,"bm":0,"completed":true},{"ddd":0,"ind":10,"ty":4,"nm":"Shadow","parent":9,"sr":1,"ks":{"o":{"a":0,"k":20,"ix":11},"r":{"a":0,"k":0,"ix":10},"p":{"a":0,"k":[537.458,1023.537,0],"ix":2},"a":{"a":0,"k":[56,418,0],"ix":1},"s":{"a":0,"k":[92.999,74.574,100],"ix":6}},"ao":0,"shapes":[{"ty":"gr","it":[{"d":1,"ty":"el","s":{"a":0,"k":[872,84],"ix":2},"p":{"a":0,"k":[0,0],"ix":3},"nm":"Ellipse Path 1","mn":"ADBE Vector Shape - Ellipse","hd":false,"_render":true},{"ty":"fl","c":{"a":0,"k":[0,0.1686,0.1686,1],"ix":4},"o":{"a":0,"k":100,"ix":5},"r":1,"bm":0,"nm":"Fill 1","mn":"ADBE Vector Graphic - Fill","hd":false,"_render":true},{"ty":"tr","p":{"a":0,"k":[56,418],"ix":2},"a":{"a":0,"k":[0,0],"ix":1},"s":{"a":0,"k":[100,100],"ix":3},"r":{"a":0,"k":0,"ix":6},"o":{"a":0,"k":100,"ix":7},"sk":{"a":0,"k":0,"ix":4},"sa":{"a":0,"k":0,"ix":5},"nm":"Transform","_render":true}],"nm":"Ellipse 1","np":3,"cix":2,"bm":0,"ix":1,"mn":"ADBE Vector Group","hd":false,"_render":true}],"ip":0,"op":120.0000048877,"st":0,"bm":0,"completed":true},{"ddd":0,"ind":11,"ty":4,"nm":"Particles","parent":9,"sr":1,"ks":{"o":{"a":0,"k":100,"ix":11},"r":{"a":0,"k":0,"ix":10},"p":{"a":0,"k":[546.645,650.604,0],"ix":2},"a":{"a":0,"k":[0,0,0],"ix":1},"s":{"a":0,"k":[125,125,100],"ix":6}},"ao":0,"shapes":[{"ty":"gr","it":[{"ty":"sr","sy":1,"d":1,"pt":{"a":0,"k":5,"ix":3},"p":{"a":0,"k":[0,0],"ix":4},"r":{"a":0,"k":0,"ix":5},"ir":{"a":0,"k":17.889,"ix":6},"is":{"a":0,"k":0,"ix":8},"or":{"a":0,"k":35.777,"ix":7},"os":{"a":0,"k":0,"ix":9},"ix":1,"nm":"Polystar Path 1","mn":"ADBE Vector Shape - Star","hd":false,"_render":true},{"ty":"fl","c":{"a":0,"k":[0.5725,0.6549,0.9961,1],"ix":4},"o":{"a":0,"k":100,"ix":5},"r":1,"bm":0,"nm":"Fill 1","mn":"ADBE Vector Graphic - Fill","hd":false,"_render":true},{"ty":"tr","p":{"a":1,"k":[{"i":{"x":0.833,"y":0.833},"o":{"x":0.167,"y":0.167},"t":0,"s":[-322,-122],"to":null,"ti":null},{"i":{"x":0.833,"y":0.833},"o":{"x":0.167,"y":0.167},"t":60,"s":[-340,-56],"to":null,"ti":null},{"t":119.000004846969,"s":[-322,-122]}],"ix":2},"a":{"a":0,"k":[0,0],"ix":1},"s":{"a":0,"k":[59.02,59.02],"ix":3},"r":{"a":0,"k":0,"ix":6},"o":{"a":0,"k":100,"ix":7},"sk":{"a":0,"k":0,"ix":4},"sa":{"a":0,"k":0,"ix":5},"nm":"Transform","_render":true}],"nm":"Polystar 3","np":3,"cix":2,"bm":0,"ix":1,"mn":"ADBE Vector Group","hd":false,"_render":true},{"ty":"gr","it":[{"ty":"sr","sy":1,"d":1,"pt":{"a":0,"k":5,"ix":3},"p":{"a":0,"k":[0,0],"ix":4},"r":{"a":0,"k":0,"ix":5},"ir":{"a":0,"k":17.889,"ix":6},"is":{"a":0,"k":0,"ix":8},"or":{"a":0,"k":35.777,"ix":7},"os":{"a":0,"k":0,"ix":9},"ix":1,"nm":"Polystar Path 1","mn":"ADBE Vector Shape - Star","hd":false,"_render":true},{"ty":"fl","c":{"a":0,"k":[0.5725,0.6549,0.9961,1],"ix":4},"o":{"a":0,"k":100,"ix":5},"r":1,"bm":0,"nm":"Fill 1","mn":"ADBE Vector Graphic - Fill","hd":false,"_render":true},{"ty":"tr","p":{"a":1,"k":[{"i":{"x":0.833,"y":0.833},"o":{"x":0.167,"y":0.167},"t":0,"s":[-172,-404],"to":null,"ti":null},{"i":{"x":0.833,"y":0.833},"o":{"x":0.167,"y":0.167},"t":60,"s":[-226,-328],"to":null,"ti":null},{"t":119.000004846969,"s":[-172,-404]}],"ix":2},"a":{"a":0,"k":[0,0],"ix":1},"s":{"a":0,"k":[100,100],"ix":3},"r":{"a":0,"k":0,"ix":6},"o":{"a":0,"k":100,"ix":7},"sk":{"a":0,"k":0,"ix":4},"sa":{"a":0,"k":0,"ix":5},"nm":"Transform","_render":true}],"nm":"Polystar 2","np":3,"cix":2,"bm":0,"ix":2,"mn":"ADBE Vector Group","hd":false,"_render":true},{"ty":"gr","it":[{"ty":"sr","sy":1,"d":1,"pt":{"a":0,"k":5,"ix":3},"p":{"a":0,"k":[0,0],"ix":4},"r":{"a":0,"k":0,"ix":5},"ir":{"a":0,"k":17.889,"ix":6},"is":{"a":0,"k":0,"ix":8},"or":{"a":0,"k":35.777,"ix":7},"os":{"a":0,"k":0,"ix":9},"ix":1,"nm":"Polystar Path 1","mn":"ADBE Vector Shape - Star","hd":false,"_render":true},{"ty":"fl","c":{"a":0,"k":[0.5725,0.6549,0.9961,1],"ix":4},"o":{"a":0,"k":100,"ix":5},"r":1,"bm":0,"nm":"Fill 1","mn":"ADBE Vector Graphic - Fill","hd":false,"_render":true},{"ty":"tr","p":{"a":1,"k":[{"i":{"x":0.833,"y":0.833},"o":{"x":0.167,"y":0.167},"t":0,"s":[254,-182],"to":null,"ti":null},{"i":{"x":0.833,"y":0.833},"o":{"x":0.167,"y":0.167},"t":60,"s":[317,-182],"to":null,"ti":null},{"t":119.000004846969,"s":[254,-182]}],"ix":2},"a":{"a":0,"k":[0,0],"ix":1},"s":{"a":0,"k":[73.958,73.958],"ix":3},"r":{"a":0,"k":0,"ix":6},"o":{"a":0,"k":100,"ix":7},"sk":{"a":0,"k":0,"ix":4},"sa":{"a":0,"k":0,"ix":5},"nm":"Transform","_render":true}],"nm":"Polystar 1","np":3,"cix":2,"bm":0,"ix":3,"mn":"ADBE Vector Group","hd":false,"_render":true},{"ty":"gr","it":[{"d":1,"ty":"el","s":{"a":0,"k":[84,84],"ix":2},"p":{"a":0,"k":[0,0],"ix":3},"nm":"Ellipse Path 1","mn":"ADBE Vector Shape - Ellipse","hd":false,"_render":true},{"ty":"fl","c":{"a":0,"k":[0.5725,0.6549,0.9961,1],"ix":4},"o":{"a":0,"k":100,"ix":5},"r":1,"bm":0,"nm":"Fill 1","mn":"ADBE Vector Graphic - Fill","hd":false,"_render":true},{"ty":"tr","p":{"a":1,"k":[{"i":{"x":0.833,"y":0.833},"o":{"x":0.167,"y":0.167},"t":0,"s":[-222,190],"to":null,"ti":null},{"i":{"x":0.833,"y":0.833},"o":{"x":0.167,"y":0.167},"t":60,"s":[-222,179],"to":null,"ti":null},{"t":119.000004846969,"s":[-222,190]}],"ix":2},"a":{"a":0,"k":[0,0],"ix":1},"s":{"a":0,"k":[47.059,47.059],"ix":3},"r":{"a":0,"k":0,"ix":6},"o":{"a":0,"k":100,"ix":7},"sk":{"a":0,"k":0,"ix":4},"sa":{"a":0,"k":0,"ix":5},"nm":"Transform","_render":true}],"nm":"Ellipse 3","np":3,"cix":2,"bm":0,"ix":4,"mn":"ADBE Vector Group","hd":false,"_render":true},{"ty":"gr","it":[{"d":1,"ty":"el","s":{"a":0,"k":[84,84],"ix":2},"p":{"a":0,"k":[0,0],"ix":3},"nm":"Ellipse Path 1","mn":"ADBE Vector Shape - Ellipse","hd":false,"_render":true},{"ty":"fl","c":{"a":0,"k":[0.5725,0.6549,0.9961,1],"ix":4},"o":{"a":0,"k":100,"ix":5},"r":1,"bm":0,"nm":"Fill 1","mn":"ADBE Vector Graphic - Fill","hd":false,"_render":true},{"ty":"tr","p":{"a":1,"k":[{"i":{"x":0.833,"y":0.833},"o":{"x":0.167,"y":0.167},"t":0,"s":[148,-386],"to":null,"ti":null},{"i":{"x":0.833,"y":0.833},"o":{"x":0.167,"y":0.167},"t":60,"s":[133,-340],"to":null,"ti":null},{"t":119.000004846969,"s":[148,-386]}],"ix":2},"a":{"a":0,"k":[0,0],"ix":1},"s":{"a":0,"k":[47.059,47.059],"ix":3},"r":{"a":0,"k":0,"ix":6},"o":{"a":0,"k":100,"ix":7},"sk":{"a":0,"k":0,"ix":4},"sa":{"a":0,"k":0,"ix":5},"nm":"Transform","_render":true}],"nm":"Ellipse 4","np":3,"cix":2,"bm":0,"ix":5,"mn":"ADBE Vector Group","hd":false,"_render":true},{"ty":"gr","it":[{"d":1,"ty":"el","s":{"a":0,"k":[84,84],"ix":2},"p":{"a":0,"k":[0,0],"ix":3},"nm":"Ellipse Path 1","mn":"ADBE Vector Shape - Ellipse","hd":false,"_render":true},{"ty":"fl","c":{"a":0,"k":[0.5725,0.6549,0.9961,1],"ix":4},"o":{"a":0,"k":100,"ix":5},"r":1,"bm":0,"nm":"Fill 1","mn":"ADBE Vector Graphic - Fill","hd":false,"_render":true},{"ty":"tr","p":{"a":1,"k":[{"i":{"x":0.833,"y":0.833},"o":{"x":0.167,"y":0.167},"t":0,"s":[-302,30],"to":null,"ti":null},{"i":{"x":0.833,"y":0.833},"o":{"x":0.167,"y":0.167},"t":60,"s":[-205,-66],"to":null,"ti":null},{"t":119.000004846969,"s":[-302,30]}],"ix":2},"a":{"a":0,"k":[0,0],"ix":1},"s":{"a":0,"k":[47.059,47.059],"ix":3},"r":{"a":0,"k":0,"ix":6},"o":{"a":0,"k":100,"ix":7},"sk":{"a":0,"k":0,"ix":4},"sa":{"a":0,"k":0,"ix":5},"nm":"Transform","_render":true}],"nm":"Ellipse 2","np":3,"cix":2,"bm":0,"ix":6,"mn":"ADBE Vector Group","hd":false,"_render":true},{"ty":"gr","it":[{"d":1,"ty":"el","s":{"a":0,"k":[84,84],"ix":2},"p":{"a":0,"k":[0,0],"ix":3},"nm":"Ellipse Path 1","mn":"ADBE Vector Shape - Ellipse","hd":false,"_render":true},{"ty":"fl","c":{"a":0,"k":[0.5725,0.6549,0.9961,1],"ix":4},"o":{"a":0,"k":100,"ix":5},"r":1,"bm":0,"nm":"Fill 1","mn":"ADBE Vector Graphic - Fill","hd":false,"_render":true},{"ty":"tr","p":{"a":1,"k":[{"i":{"x":0.833,"y":0.833},"o":{"x":0.167,"y":0.167},"t":0,"s":[274,34],"to":null,"ti":null},{"i":{"x":0.833,"y":0.833},"o":{"x":0.167,"y":0.167},"t":60,"s":[211,-15],"to":null,"ti":null},{"t":119.000004846969,"s":[274,34]}],"ix":2},"a":{"a":0,"k":[0,0],"ix":1},"s":{"a":0,"k":[100,100],"ix":3},"r":{"a":0,"k":0,"ix":6},"o":{"a":0,"k":100,"ix":7},"sk":{"a":0,"k":0,"ix":4},"sa":{"a":0,"k":0,"ix":5},"nm":"Transform","_render":true}],"nm":"Ellipse 1","np":3,"cix":2,"bm":0,"ix":7,"mn":"ADBE Vector Group","hd":false,"_render":true}],"ip":0,"op":120.0000048877,"st":0,"bm":0,"completed":true}],"markers":[],"__complete":true}